slowapi/__init__.py
slowapi/errors.py
slowapi/extension.py
slowapi/middleware.py
slowapi/py.typed
slowapi/util.py
slowapi/wrappers.py
slowapi-0.1.3.dist-info/LICENSE
slowapi-0.1.3.dist-info/WHEEL
slowapi-0.1.3.dist-info/METADATA
slowapi-0.1.3.dist-info/RECORD
