Metadata-Version: 2.1
Name: slowapi
Version: 0.1.3
Summary: A rate limiting extension for Starlette and Fastapi
Home-page: https://github.com/laurents/slowapi
License: MIT
Author: Laurent Savaete
Author-email: laurent@where.tf
Requires-Python: >=3.6,<4.0
Classifier: License :: OSI Approved :: MIT License
Classifier: Programming Language :: Python :: 3
Classifier: Programming Language :: Python :: 3.6
Classifier: Programming Language :: Python :: 3.7
Classifier: Programming Language :: Python :: 3.8
Classifier: Programming Language :: Python :: 3.9
Requires-Dist: limits (>=1.5,<2.0)
Requires-Dist: redis (>=3.4.1,<4.0.0)
Project-URL: Documentation, https://slowapi.readthedocs.io/en/latest/
Project-URL: Repository, https://github.com/laurents/slowapi
